mm_dev_mcp/__init__.py
mm_dev_mcp/server.py
mm_dev_mcp/sse.py
mm_dev_mcp/stdio.py
yonyou_mm_dev_mcp-0.1.10.dist-info/METADATA
yonyou_mm_dev_mcp-0.1.10.dist-info/WHEEL
yonyou_mm_dev_mcp-0.1.10.dist-info/entry_points.txt
yonyou_mm_dev_mcp-0.1.10.dist-info/top_level.txt
yonyou_mm_dev_mcp-0.1.10.dist-info/RECORD
