Metadata-Version: 2.4
Name: yonyou-mm-dev-mcp
Version: 0.1.10
Summary: 制造云开发者平台
Author-email: yungangwu <yungangwu@gmail.com>
Requires-Python: >=3.13
Requires-Dist: fastmcp>=2.8.1
Requires-Dist: httpx>=0.28.1
